<?xml version="1.0" encoding="UTF-8"?><wowhead><item id="4343"><name><![CDATA[Brown Linen Pants]]></name><level>10</level><quality id="2">Uncommon</quality><class id="4"><![CDATA[Armor]]></class><subclass id="1"><![CDATA[Cloth Armor]]></subclass><icon displayId="1883">inv_pants_06</icon><inventorySlot id="7">Legs</inventorySlot><htmlTooltip><![CDATA[<table><tr><td><!--nstart--><b class="q2">Brown Linen Pants</b><!--nend--><!--ndstart--><!--ndend--><span style="color: #ffd100"><br />Item Level <!--ilvl-->10</span><br /><!--bo-->Binds when equipped<table width="100%"><tr><td>Legs</td><th><!--scstart4:1--><span class="q1">Cloth</span><!--scend--></th></tr></table><span><!--amr-->4 Armor</span><br /><span><!--stat5-->+1 Intellect</span><!--ebstats--><!--egstats--><!--e--><!--ps--><br />Durability 55 / 55</td></tr></table><table><tr><td>Requires Level <!--rlvl-->5<div class="whtt-sellprice">Sell Price: <span class="moneysilver">1</span> <span class="moneycopper">76</span></div></td></tr></table>]]></htmlTooltip><json><![CDATA["appearances":{"0":[1883,""]},"armor":4,"classs":4,"displayid":1883,"flags2":8192,"id":4343,"level":10,"name":"6Brown Linen Pants","reqlevel":5,"slot":7,"slotbak":7,"source":[1],"sourcemore":[{"c":11,"icon":"inv_pants_06","n":"Brown Linen Pants","s":197,"t":6,"ti":3914}],"subclass":1]]></json><jsonEquip><![CDATA["appearances":{"0":[1883,""]},"armor":4,"avgbuyout":77365,"displayid":1883,"dura":55,"int":1,"reqlevel":5,"sellprice":176,"slotbak":7]]></jsonEquip><createdBy><spell id="3914" name="Brown Linen Pants" icon="inv_pants_06" minCount="1" maxCount="1"><reagent id="2996" name="Bolt of Linen Cloth" quality="1" icon="inv_fabric_linen_02" count="2" /><reagent id="2320" name="Coarse Thread" quality="1" icon="inv_fabric_linen_03" count="1" /></spell></createdBy><link>http://www.wowhead.com/item=4343</link></item></wowhead>