<?xml version="1.0" encoding="UTF-8"?><wowhead><item id="13340"><name><![CDATA[Cape of the Black Baron]]></name><level>53</level><quality id="3">Rare</quality><class id="4"><![CDATA[Armor]]></class><subclass id="-6"><![CDATA[Cloaks]]></subclass><icon displayId="24013">inv_misc_cape_20</icon><inventorySlot id="16">Back</inventorySlot><htmlTooltip><![CDATA[<table><tr><td><!--nstart--><b class="q3">Cape of the Black Baron</b><!--nend--><!--ndstart--><!--ndend--><span style="color: #ffd100"><br />Item Level <!--ilvl-->53</span><br /><!--bo-->Binds when picked up<table width="100%"><tr><td>Back</td></table><span><!--amr-->7 Armor</span><br /><span><!--stat3-->+8 Agility</span><br /><span><!--stat7-->+8 Stamina</span><!--ebstats--><br /><span class="q2">+<!--rtg36-->8 Haste&nbsp;<small>(<!--rtg%36-->0.02%&nbsp;@&nbsp;L<!--lvl-->110)</small></span><!--egstats--><!--e--><!--ps--></td></tr></table><table><tr><td>Requires Level <!--rlvl-->48<div class="whtt-sellprice">Sell Price: <span class="moneygold">1</span> <span class="moneysilver">68</span> <span class="moneycopper">73</span></div><div class="whtt-extra whtt-droppedby">Dropped by: Lord Aurius Rivendare</div><div class="whtt-extra whtt-dropchance">Drop Chance: 12.09%</div></td></tr></table><!--i?13340:1:110:48-->]]></htmlTooltip><json><![CDATA["appearances":{"0":[24013,""]},"armor":7,"classs":4,"displayid":24013,"flags2":8192,"id":13340,"level":53,"name":"5Cape of the Black Baron","reqlevel":48,"slot":16,"slotbak":16,"source":[2],"sourcemore":[{"bd":1,"dd":-1,"n":"Lord Aurius Rivendare","t":1,"ti":45412,"z":2017}],"subclass":-6]]></json><jsonEquip><![CDATA["agi":8,"appearances":{"0":[24013,""]},"armor":7,"displayid":24013,"hastertng":8,"reqlevel":48,"sellprice":16873,"slotbak":16,"sta":8]]></jsonEquip><link>http://www.wowhead.com/item=13340</link></item></wowhead>